README.md
setup.py
forpay_client/__init__.py
forpay_client/forpay.py
forpay_client/helpers.py
forpay_client/http_base.py
forpay_client.egg-info/PKG-INFO
forpay_client.egg-info/SOURCES.txt
forpay_client.egg-info/dependency_links.txt
forpay_client.egg-info/requires.txt
forpay_client.egg-info/top_level.txt
forpay_client/exception/__init__.py
forpay_client/exception/err_code.py
forpay_client/exception/err_msg.py
forpay_client/exception/exception.py