Metadata-Version: 1.1
Name: forpay-client
Version: 1.0.24
Summary: The client module of Forpay Python sdk
Home-page: https://github.com/hacfox/forpay_client.git
Author: bozimeile
Author-email: zz.hacfox@gmail.com
License: MIT License
Keywords: forpay,forpay-client,sdk
Platform: any
Classifier: Development Status :: 4 - Beta
Classifier: Operating System :: OS Independent
Classifier: Intended Audience :: Developers
Classifier: License :: OSI Approved :: MIT License
Classifier: Programming Language :: Python
Classifier: Programming Language :: Python :: 3.6
